netkiller/__init__.py
netkiller/cicd.py
netkiller/docker.py
netkiller/git.py
netkiller/gitlab.py
netkiller/kubernetes.py
netkiller/mongo.py
netkiller/mysql.py
netkiller/nacos.py
netkiller/nagios.py
netkiller/pipeline.py
netkiller/podman.py
netkiller/rsync.py
netkiller/svg.py
netkiller/wework.py
netkiller/whiptail.py
netkiller_devops-0.7.12.data/data/etc/deployment.cfg
netkiller_devops-0.7.12.data/data/etc/dump.ini.sample
netkiller_devops-0.7.12.data/data/etc/logviewer.ini
netkiller_devops-0.7.12.data/data/etc/mongo.ini.sample
netkiller_devops-0.7.12.data/data/etc/notification.ini
netkiller_devops-0.7.12.data/data/etc/os.ini
netkiller_devops-0.7.12.data/data/etc/schedule.cfg
netkiller_devops-0.7.12.data/data/etc/task.cfg
netkiller_devops-0.7.12.data/data/libexec/devops/backup.mysql.gpg.sh
netkiller_devops-0.7.12.data/data/libexec/devops/backup.mysql.sh
netkiller_devops-0.7.12.data/data/libexec/devops/backup.mysql.struct.sh
netkiller_devops-0.7.12.data/data/share/devops.sh
netkiller_devops-0.7.12.data/data/share/example.com.ini
netkiller_devops-0.7.12.data/data/share/devops/voice.md
netkiller_devops-0.7.12.data/data/share/devops/wechat.md
netkiller_devops-0.7.12.data/scripts/backup
netkiller_devops-0.7.12.data/scripts/chpasswd.sh
netkiller_devops-0.7.12.data/scripts/cicd
netkiller_devops-0.7.12.data/scripts/deployment
netkiller_devops-0.7.12.data/scripts/dingtalk
netkiller_devops-0.7.12.data/scripts/exceldiff
netkiller_devops-0.7.12.data/scripts/gitsync
netkiller_devops-0.7.12.data/scripts/logviewer
netkiller_devops-0.7.12.data/scripts/logviewer.docker
netkiller_devops-0.7.12.data/scripts/logviewer.kubectl
netkiller_devops-0.7.12.data/scripts/lrsync
netkiller_devops-0.7.12.data/scripts/matrixpasswd
netkiller_devops-0.7.12.data/scripts/mdump
netkiller_devops-0.7.12.data/scripts/merge
netkiller_devops-0.7.12.data/scripts/mysqlshell
netkiller_devops-0.7.12.data/scripts/nacos
netkiller_devops-0.7.12.data/scripts/osconf
netkiller_devops-0.7.12.data/scripts/randpasswd
netkiller_devops-0.7.12.dist-info/licenses/LICENSE
netkiller_devops-0.7.12.dist-info/METADATA
netkiller_devops-0.7.12.dist-info/WHEEL
netkiller_devops-0.7.12.dist-info/top_level.txt
netkiller_devops-0.7.12.dist-info/RECORD
