Metadata-Version: 2.4
Name: netkiller-devops
Version: 0.7.12
Summary: DevOps of useful deployment and automation
Home-page: https://www.netkiller.cn
Author: Neo Chen
Author-email: Neo <netkiller@msn.com>
License-Expression: MIT
Project-URL: Homepage, https://www.netkiller.cn
Project-URL: Issues, https://github.com/netkiller/netkiller-devops/issues
Classifier: Programming Language :: Python :: 3
Classifier: Operating System :: OS Independent
Requires-Python: >=3.12
License-File: LICENSE
Requires-Dist: ruamel.yaml
Requires-Dist: requests
Requires-Dist: redis
Requires-Dist: pyttsx3
Requires-Dist: simple_term_menu
Requires-Dist: prompt_toolkit
Dynamic: author
Dynamic: home-page
Dynamic: license-file
